pycmd2/__init__.py
pycmd2/cli.py
pycmd2/client.py
pycmd2/compat.py
pycmd2/config.py
pycmd2/runner.py
pycmd2/utils.py
pycmd2/backend/__init__.py
pycmd2/backend/cli.py
pycmd2/backend/database.py
pycmd2/backend/api/__init__.py
pycmd2/backend/api/client.py
pycmd2/backend/core/__init__.py
pycmd2/backend/models/__init__.py
pycmd2/backend/models/user.py
pycmd2/commands/__init__.py
pycmd2/commands/dev/__init__.py
pycmd2/commands/dev/piptools.py
pycmd2/commands/dev/ssh_copy_id.py
pycmd2/commands/dev/envtools/__init__.py
pycmd2/commands/dev/envtools/base.py
pycmd2/commands/dev/envtools/cli.py
pycmd2/commands/dev/envtools/python.py
pycmd2/commands/dev/envtools/rust.py
pycmd2/commands/dev/gittools/__init__.py
pycmd2/commands/dev/gittools/cli.py
pycmd2/commands/dev/gittools/git_add.py
pycmd2/commands/dev/gittools/git_clean.py
pycmd2/commands/dev/gittools/git_init.py
pycmd2/commands/dev/gittools/git_push_all.py
pycmd2/commands/dev/makepython/__init__.py
pycmd2/commands/dev/makepython/cli.py
pycmd2/commands/dev/makepython/update.py
pycmd2/commands/office/__init__.py
pycmd2/commands/office/doc_diff.py
pycmd2/commands/office/image_gray.py
pycmd2/commands/office/image_to_pdf.py
pycmd2/commands/office/llama_client.py
pycmd2/commands/office/llama_quantize.py
pycmd2/commands/office/llama_server.py
pycmd2/commands/office/pdf_crypt.py
pycmd2/commands/office/pdf_merge.py
pycmd2/commands/office/pdf_split.py
pycmd2/commands/office/video_converter.py
pycmd2/commands/office/mindnote/__init__.py
pycmd2/commands/office/mindnote/cli.py
pycmd2/commands/office/mindnote/connection.py
pycmd2/commands/office/mindnote/mainwindow.py
pycmd2/commands/office/mindnote/node.py
pycmd2/commands/office/mindnote/pyproject.toml
pycmd2/commands/office/pdftools/__init__.py
pycmd2/commands/office/pdftools/cli.py
pycmd2/commands/office/tests/__init__.py
pycmd2/commands/office/tests/test_image_gray.py
pycmd2/commands/office/tests/test_image_to_pdf.py
pycmd2/commands/office/tests/test_pdf_crypt.py
pycmd2-0.7.7.dist-info/METADATA
pycmd2-0.7.7.dist-info/WHEEL
pycmd2-0.7.7.dist-info/entry_points.txt
pycmd2-0.7.7.dist-info/licenses/AUTHORS.rst
pycmd2-0.7.7.dist-info/licenses/LICENSE
pycmd2-0.7.7.dist-info/RECORD
