Metadata-Version: 2.4
Name: pycmd2
Version: 0.7.7
Summary: Command tools build with python.
Project-URL: Documentation, https://pycmd2.readthedocs.io/zh-cn/stable/
Project-URL: Issues, https://gitee.com/gooker_young/pycmd2/issues
Project-URL: Repository, https://gitee.com/gooker_young/pycmd2
Author-email: gooker_young <gooker_young@qq.com>
Maintainer-email: gooker_young <gooker_young@qq.com>
License: MIT license
License-File: AUTHORS.rst
License-File: LICENSE
Requires-Python: >=3.8
Requires-Dist: fastapi-offline>=1.7.5
Requires-Dist: fastapi[all]>=0.122.0
Requires-Dist: pywebview>=6.1
Requires-Dist: rich>=13.9.4
Requires-Dist: tomli-w>=1.0.0; python_full_version < '3.11'
Requires-Dist: tomli>=2.2.1; python_full_version < '3.11'
Requires-Dist: typer>=0.15.1
Provides-Extra: all
Requires-Dist: httpx>=0.24.0; extra == 'all'
Requires-Dist: matplotlib>=3.7.5; extra == 'all'
Requires-Dist: nicegui>=2.24.2; extra == 'all'
Requires-Dist: numpy>=1.24.4; extra == 'all'
Requires-Dist: pandas>=2.0.3; extra == 'all'
Requires-Dist: pillow>=10; extra == 'all'
Requires-Dist: psutil>=7.1.3; extra == 'all'
Requires-Dist: pymupdf>=1.24.11; extra == 'all'
Requires-Dist: pypdf>=5.9.0; extra == 'all'
Requires-Dist: pyqt5-sip~=12.9.0; extra == 'all'
Requires-Dist: pyqt5-stubs~=5.14.0; extra == 'all'
Requires-Dist: pyqt5~=5.14.0; extra == 'all'
Requires-Dist: pywin32>=311; (platform_system == 'Windows') and extra == 'all'
Requires-Dist: qdarkstyle>=3.2.3; extra == 'all'
Requires-Dist: scipy>=1.10.1; extra == 'all'
Requires-Dist: sqlmodel>=0.0.27; extra == 'all'
Requires-Dist: torch~=2.1.0; extra == 'all'
Provides-Extra: gui
Requires-Dist: nicegui>=2.24.2; extra == 'gui'
Requires-Dist: pyqt5-sip~=12.9.0; extra == 'gui'
Requires-Dist: pyqt5-stubs~=5.14.0; extra == 'gui'
Requires-Dist: pyqt5~=5.14.0; extra == 'gui'
Requires-Dist: qdarkstyle>=3.2.3; extra == 'gui'
Provides-Extra: office
Requires-Dist: httpx>=0.24.0; extra == 'office'
Requires-Dist: numpy>=1.24.4; extra == 'office'
Requires-Dist: pandas>=2.0.3; extra == 'office'
Requires-Dist: pillow>=10; extra == 'office'
Requires-Dist: psutil>=7.1.3; extra == 'office'
Requires-Dist: pymupdf>=1.24.11; extra == 'office'
Requires-Dist: pypdf>=5.9.0; extra == 'office'
Requires-Dist: pywin32>=311; (platform_system == 'Windows') and extra == 'office'
Requires-Dist: sqlmodel>=0.0.27; extra == 'office'
Provides-Extra: simulation
Requires-Dist: matplotlib>=3.7.5; extra == 'simulation'
Requires-Dist: scipy>=1.10.1; extra == 'simulation'
Requires-Dist: torch~=2.1.0; extra == 'simulation'
